<?xml version="1.0" encoding="utf-8" ?>
<hibernate-mapping xmlns="urn:nhibernate-mapping-2.2" namespace="ZhiFang.Entity.RBAC" assembly="ZhiFang.Entity.RBAC">
  <class name="BlooddocGrade" table="[dbo].[Blood_docGrade]">
    <id name="Id" column="[GradeNo]" type="Int64">
      <generator class="assigned" />
    </id>
    <version name="DataTimeStamp" column="[DataTimeStamp]" type="BinaryBlob" generated="always" unsaved-value="null" />
    <property name="CName" column="[GradeName]" type="String" not-null="false" length="50" />
    <property name="BCount" column="[BCount]" type="Double" not-null="false" length="8" />
    <property name="DispOrder" column="[dispOrder]" type="Int32" not-null="false" length="4" />
    <property name="LabID" column="[LabID]" type="Int64" not-null="false" length="8" />
    <property name="DataAddTime" column="[DataAddTime]" type="DateTime" not-null="false" length="8" />
    <property name="LowLimit" column="[LowLimit]" type="Double" not-null="false" length="8" />
    <property name="UpperLimit" column="[UpperLimit]" type="Double" not-null="false" length="8" />
  </class>
</hibernate-mapping>
